concise/__init__.py
concise/dataset.py
concise/main.py
concise/pretrained.py
concise/commands/__init__.py
concise/commands/download.py
concise/commands/easy_query.py
concise/commands/protein_to_codes.py
concise/commands/query.py
concise/commands/smiles_to_codes.py
concise/model/__init__.py
concise/model/concise.py
concise/model/drug_decoder.py
concise/model/fsq.py
concise_dti-1.0.0.dist-info/LICENSE
concise_dti-1.0.0.dist-info/METADATA
concise_dti-1.0.0.dist-info/WHEEL
concise_dti-1.0.0.dist-info/entry_points.txt
concise_dti-1.0.0.dist-info/top_level.txt
concise_dti-1.0.0.dist-info/RECORD
