Metadata-Version: 2.1
Name: concise_dti
Version: 1.0.0
Summary: Learning a CoNCISE language for small-molecule binding
Home-page: https://github.com/rohitsinghlab/CoNCISE
Author: Mert Erden
Author-email: merterden97@gmail.com
Classifier: Programming Language :: Python :: 3
Classifier: Programming Language :: Python :: 3 :: Only
Classifier: Programming Language :: Python :: Implementation :: CPython
Classifier: Programming Language :: Python :: Implementation :: PyPy
Requires-Python: >=3.12
License-File: LICENSE
Requires-Dist: numpy<2
Requires-Dist: pandas
Requires-Dist: scikit-learn
Requires-Dist: torch
Requires-Dist: transformers
Requires-Dist: tqdm
Requires-Dist: matplotlib
Requires-Dist: seaborn
Requires-Dist: rdkit
Requires-Dist: pytorch-lightning
Requires-Dist: raygun
Requires-Dist: typer
Requires-Dist: hydra-core
Requires-Dist: molfeat
